<?xml version="1.0" encoding="UTF-8"?>

<persistence version="2.0" xmlns="http://java.sun.com/xml/ns/persistence" xmlns:xsi="http://www.w3.org/2001/XMLSchema-instance" xsi:schemaLocation="http://java.sun.com/xml/ns/persistence         http://java.sun.com/xml/ns/persistence/persistence_2_0.xsd">
  <!-- Unidade de persistencia -->
  <!-- Esse nome será usado no persistence do EntityManagerFactory -->
  <persistence-unit name="prj_integrador_IV_PU">
    <!-- Implementação do JPA -->
    <provider>org.hibernate.jpa.HibernatePersistenceProvider</provider>
    <!-- Lista de entidades -->
     <!-- Sempre adicionar sua classes aqui se não não funfa -->
    <class>br.edu.unifacear.projetointegrador4.entity.Montadora</class>
    <class>br.edu.unifacear.projetointegrador4.entity.Aplicacao</class>
  
    <class>br.edu.unifacear.projetointegrador4.entity.Cargo</class>
    <class>br.edu.unifacear.projetointegrador4.entity.Cliente</class>    
    <class>br.edu.unifacear.projetointegrador4.entity.Funcionario</class>
    <class>br.edu.unifacear.projetointegrador4.entity.LinhaDeVeiculo</class>
    <class>br.edu.unifacear.projetointegrador4.entity.Modelo</class>
    <class>br.edu.unifacear.projetointegrador4.entity.Peca</class>
    <class>br.edu.unifacear.projetointegrador4.entity.PedidoDeVenda</class>
    <class>br.edu.unifacear.projetointegrador4.entity.StatusPV</class>
    <class>br.edu.unifacear.projetointegrador4.entity.Telefone</class>
    <class>br.edu.unifacear.projetointegrador4.entity.TipoCliente</class>
   
    <properties>
      <!-- Propriedades JDBC -->
      <property name="javax.persistence.jdbc.driver" value="com.mysql.jdbc.Driver"/>
     
      <property name="javax.persistence.jdbc.url" value="jdbc:mysql://localhost/prjintegradoriv"/> <!-- aqui no final vai o nome do banco  -->
      <property name="javax.persistence.jdbc.user" value="root"/>
      <property name="javax.persistence.jdbc.password" value=""/>
      <!-- Configurações específicas do Hibernate -->
      <property name="hibernate.dialect" value="org.hibernate.dialect.MySQL5InnoDBDialect"/>
      <property name="hibernate.hbm2ddl.auto" value="update"/>
      <property name="hibernate.show_sql" value="false"/>
      <property name="hibernate.format_sql" value="true"/>
    </properties>
  </persistence-unit>
</persistence>